nurnpy/Apriori.py
nurnpy/Excercise1.py
nurnpy/Excercise2.py
nurnpy/Hierarchial_Clustering.py
nurnpy/__init__.py
nurnpy/dbscan.py
nurnpy/decision_tree.py
nurnpy/ds_creation.py
nurnpy/eda.py
nurnpy/eda_dummy.py
nurnpy/fp-growth.py
nurnpy/hierarchical.py
nurnpy/k-means.py
nurnpy/naive-bayes-diabetes.py
nurnpy/naive_bayes.py
spenurnpy-0.1.0.dist-info/licenses/LICENSE
spenurnpy-0.1.0.dist-info/METADATA
spenurnpy-0.1.0.dist-info/WHEEL
spenurnpy-0.1.0.dist-info/top_level.txt
spenurnpy-0.1.0.dist-info/RECORD
